snipshue/Snipsspec
snipshue/__init__.py
snipshue/snipshue.py
snipshue-1.0.dist-info/DESCRIPTION.rst
snipshue-1.0.dist-info/METADATA
snipshue-1.0.dist-info/RECORD
snipshue-1.0.dist-info/WHEEL
snipshue-1.0.dist-info/metadata.json
snipshue-1.0.dist-info/top_level.txt
