Metadata-Version: 2.0
Name: snipshue
Version: 1.0
Summary: Philips Hue skill for Snips
Home-page: https://github.com/snipsco/snips-skill-hue
Author: Michael Fester
Author-email: michael.fester@gmail.com
License: MIT
Keywords: snips
Platform: UNKNOWN
Requires-Dist: requests (==2.6.0)
